nbg/__init__.py
nbg/account_information.py
nbg/auth/__init__.py
nbg/auth/certs/nbg-qseal-production.cer
nbg/auth/certs/nbg-qseal-sandbox.cer
nbg/auth/consent.py
nbg/auth/consent_test.py
nbg/auth/exceptions.py
nbg/auth/oauth.py
nbg/auth/oauth_test.py
nbg/auth/signature.py
nbg/auth/signature_test.py
nbg/base/__init__.py
nbg/base/client.py
nbg/base/decorators.py
nbg/base/environment.py
nbg/base/environment_test.py
nbg/base/exceptions.py
nbg/base/utils.py
nbg/base/utils_test.py
nbg-0.7.1.dist-info/LICENSE
nbg-0.7.1.dist-info/WHEEL
nbg-0.7.1.dist-info/METADATA
nbg-0.7.1.dist-info/RECORD
