Metadata-Version: 2.1
Name: nbg
Version: 0.7.1
Summary: Official Python SDK for NBG APIs
Home-page: https://github.com/myNBGcode/nbg-python-sdk
Author: National Bank of Greece
Requires-Python: >=3.6,<4.0
Classifier: Programming Language :: Python :: 3
Classifier: Programming Language :: Python :: 3.6
Classifier: Programming Language :: Python :: 3.7
Classifier: Programming Language :: Python :: 3.8
Provides-Extra: docs
Requires-Dist: python-jose[cryptography] (>=3.1.0,<4.0.0)
Requires-Dist: requests (>=2.22.0,<3.0.0)
Requires-Dist: sphinx (>=3.0.0,<4.0.0); extra == "docs"
Project-URL: Documentation, https://nbg-python-sdk.readthedocs.io
Project-URL: Repository, https://github.com/myNBGcode/nbg-python-sdk
